{"1741963958791":{"actionType":"saveAll","createdAt":"1741963958791","actionID":"1741963958791","userID":"#TEMP","path":"system.capsules.40d453a2-0c20-44a3-80db-59709aec81bf.capsUseCodeInfo.capsUseInputs.ccc_stringValue-0.capsIptTxtValue","oldValue":"{\n     backgroundColor: \"#0a1425\", \n     width: \"100%\", \n     flexDirection: \"row\",\n     paddingVertical: 10,\n     paddingHorizontal: 5\n}","newValue":"{\n     backgroundColor: \"#0a1425\", \n     width: \"100%\", \n     flexDirection: \"row\",\n     paddingVertical: 10,\n     paddingHorizontal: 5,\n}"}}