{"1741967311086":{"actionType":"saveAll","createdAt":"1741967311086","actionID":"1741967311086","userID":"#TEMP","path":"system.capsules.d11570ae-e85c-4d14-888d-043a38278227.capsUseCodeInfo.capsUseInputs.ccc_stringValue-0.capsIptTxtValue","oldValue":"{\n     maxLength={40}\n}","newValue":"{\n     maxLength={5}\n}"},"1741967311087":{"actionType":"saveAll","createdAt":"1741967311087","actionID":"1741967311087","userID":"#TEMP","path":"system.capsules.d11570ae-e85c-4d14-888d-043a38278227.capsUseCodeInfo.capsUseDescription.en","oldValue":"","newValue":"{\n     maxLength={5}\n}"}}